ApolloPyClient/ApolloPyClient.py
ApolloPyClient/__init__.py
ApolloPyClient-0.1.2.dist-info/AUTHORS.rst
ApolloPyClient-0.1.2.dist-info/LICENSE
ApolloPyClient-0.1.2.dist-info/METADATA
ApolloPyClient-0.1.2.dist-info/WHEEL
ApolloPyClient-0.1.2.dist-info/top_level.txt
ApolloPyClient-0.1.2.dist-info/RECORD
