Metadata-Version: 2.1
Name: ApolloPyClient
Version: 0.1.2
Summary: A Python SDK that is easy to integrate with the Apollo configuration management system.
Author-email: Joey Gong <come.a.mail@gmail.com>
Maintainer-email: Joey Gong <come.a.mail@gmail.com>
License: MIT license
Project-URL: bugs, https://github.com/gcj-bit/ApolloPyClient/issues
Project-URL: changelog, https://github.com/gcj-bit/ApolloPyClient/blob/master/changelog.md
Project-URL: homepage, https://github.com/gcj-bit/ApolloPyClient
License-File: LICENSE
License-File: AUTHORS.rst
Requires-Dist: loguru
Requires-Dist: PyYAML
Requires-Dist: xmltodict
Provides-Extra: dev
Requires-Dist: pytest; extra == "dev"
Requires-Dist: ruff; extra == "dev"
